outsource/__init__.py
outsource/config.py
outsource/meta.py
outsource/scripts/.gitignore
outsource/scripts/decompression.sh
outsource/scripts/gfal_download.sh
outsource/scripts/gfal_du.sh
outsource/scripts/gfal_ls_recursive.sh
outsource/scripts/import.sbatch
outsource/scripts/raw_records_location.py
outsource/scripts/rm_unfinished.sh
outsource/scripts/submit.py
outsource/submitter.py
outsource/submitters/__init__.py
outsource/submitters/htcondor.py
outsource/submitters/relay.py
outsource/submitters/slurm.py
outsource/upload.py
outsource/utils.py
outsource/workflow/combine-wrapper.sh
outsource/workflow/combine.py
outsource/workflow/process-wrapper.sh
outsource/workflow/process.py
outsource/workflow/test_resource_usage.py
outsource/workflow/untar.sh
xe_outsource-0.4.4.dist-info/METADATA
xe_outsource-0.4.4.dist-info/WHEEL
xe_outsource-0.4.4.dist-info/entry_points.txt
xe_outsource-0.4.4.dist-info/RECORD
