Metadata-Version: 2.3
Name: xe-outsource
Version: 0.4.4
Summary: Job submission of reprocessing
Author: Outsource contributors, the XENON collaboration
Requires-Python: >=3.8,<3.13
Classifier: Development Status :: 4 - Beta
Classifier: Intended Audience :: Science/Research
Classifier: License :: OSI Approved :: BSD License
Classifier: Natural Language :: English
Classifier: Programming Language :: Python :: 3
Classifier: Programming Language :: Python :: 3.8
Classifier: Programming Language :: Python :: 3.9
Classifier: Programming Language :: Python :: 3.10
Classifier: Programming Language :: Python :: 3.11
Classifier: Programming Language :: Python :: 3.12
Classifier: Programming Language :: Python :: Implementation :: CPython
Classifier: Topic :: Scientific/Engineering :: Physics
Requires-Dist: PyYAML
Requires-Dist: numpy
Requires-Dist: tqdm
Requires-Dist: utilix (>=0.9.1)
Requires-Dist: xe-admix
Project-URL: Repository, https://github.com/XENONnT/outsource
